{"product":"butter cake","expraTime":5500000,"productId":"4hd46je9s0","discription":"Cake is a  of sweet dessert that is typically baked. In their oldest forms, cakes were modifications of breads, but cakes now cover a wide range of preparations that can be simple or elaborate, and that share features with other desserts such as pastries, meringues, custards, and pies. enjoy cake.","orderId":"zid2pfco65skfv2w59wgxitbjxx6l24tjrlah7fr","quantity":2,"email":"720b888868fc8c316fb800692bac398f27617ce8464e53ec35a4a2fa61f96e85","total":22,"state":"sold"}